Workbook

Sheet Inputs
B2: ONTERRA NIGERIA LIMITED | Marginal Field Financial Model
B3: Idea to First Oil · Investor economics under PIA 2021 · Base case (editable inputs in blue)
B5: 1 · CAPITAL COST TO FIRST OIL ($ million)
B6: License & field acquisition | C6: 8.5 | E6: Typical $7-10m for a Nigerian marginal field
B7: 3D seismic & subsurface evaluation | C7: 1.5 | E7: 3D seismic to confirm where the oil is
B8: Drilling & completion (per well) | C8: 10 | E8: Land ~$7-10m; shallow offshore up to ~$15m
B9: Topsides / surface facilities | C9: 10 | E9: Separators, tanks, flare, gensets, manifolds
B10: Evacuation / flowlines / export | C10: 7 | E10: Flowline, trucking or barging to sales point
B11: Engineering, PM & owner's costs | C11: 4 | E11: FEED, project management, owner team
B12: Pre-first-oil G&A & working capital | C12: 3 | E12: Carrying costs before production
B13: Contingency | C13: 6 | E13: ~15% of base estimate
B14: Number of development wells | C14: 1 | E14: Drilling cost scales with well count
B15: TOTAL CAPITAL TO FIRST OIL | C15: =C8*Inputs!C14+C6+C7+C9+C10+C11+C12+C13
B17: 2 · CAPEX PHASING & PRODUCTION
B18: Capex spent in Development Year 1 | C18: 0.4 | E18: Balance spent in Year 2
B19: First oil in project year | C19: 3 | E19: Years 1-2 are development
B20: Plateau production rate (per well) | C20: 3000 | E20: bopd
B21: Year-1 production (ramp-up) | C21: 0.7 | E21: Share of plateau in first oil year
B22: Plateau length | C22: 12 | E22: years
B23: Annual decline after plateau | C23: 0.08 | E23: Exponential decline
B24: Days per year | C24: 365
B25: Field life (production years) | C25: 23 | E25: Typical 20-25 years
B27: 3 · PRICE, OPEX & DISCOUNTING
B28: Oil price (flat, base case) | C28: 75 | E28: $/bbl realised
B29: Variable operating cost | C29: 20 | E29: $/bbl
B30: Fixed operating cost | C30: 8 | E30: $m per production year
B31: Investor discount rate | C31: 0.1 | E31: For NPV
B33: 4 · FISCAL TERMS (PIA 2021) — confirm with tax adviser
B34: Production royalty | C34: 0.15 | E34: Onshore 15%; shallow water 12.5%
B35: Price-based royalty | C35: 0.05 | E35: PIA: 0% at <=$50/bbl, sliding up
B36: Hydrocarbon tax (HT) | C36: 0.3 | E36: PIA onshore/shallow PML
B37: Companies income tax (CIT) | C37: 0.3 | E37: PIA: applied after HT
B38: Capital allowance period | C38: 5 | E38: years, straight-line
B40: 5 · COMMERCIAL STRUCTURE (Onterra as operator)
B41: Cost-recovery share to investor | C41: 0.8 | E41: Repays the invested capital first
B42: Cost-recovery incentive to Onterra | C42: 0.2 | E42: Operator incentive during recovery
B43: Post-recovery profit to investor | C43: 0.6 | E43: Investor share after payback
B44: Post-recovery profit to Onterra | C44: 0.4 | E44: Operator promote after payback

Sheet Model
B2: ANNUAL MODEL ($ million unless stated)
B3: Live formulas — Excel recalculates on open. Black = formula, green = from Inputs.
A5: Project year | B5: 1 | C5: 2 | D5: 3 | E5: 4 | F5: 5 | G5: 6 | H5: 7 | I5: 8 | J5: 9 | K5: 10 | L5: 11 | M5: 12 | N5: 13 | O5: 14 | P5: 15 | Q5: 16 | R5: 17 | S5: 18 | T5: 19 | U5: 20 | V5: 21 | W5: 22 | X5: 23 | Y5: 24 | Z5: 25
A6: Phase | B6: =IF(B5<Inputs!C19,"Develop",IF(B5<Inputs!C19+Inputs!C25,"Produce","-")) | C6: =IF(C5<Inputs!C19,"Develop",IF(C5<Inputs!C19+Inputs!C25,"Produce","-")) | D6: =IF(D5<Inputs!C19,"Develop",IF(D5<Inputs!C19+Inputs!C25,"Produce","-")) | E6: =IF(E5<Inputs!C19,"Develop",IF(E5<Inputs!C19+Inputs!C25,"Produce","-")) | F6: =IF(F5<Inputs!C19,"Develop",IF(F5<Inputs!C19+Inputs!C25,"Produce","-")) | G6: =IF(G5<Inputs!C19,"Develop",IF(G5<Inputs!C19+Inputs!C25,"Produce","-")) | H6: =IF(H5<Inputs!C19,"Develop",IF(H5<Inputs!C19+Inputs!C25,"Produce","-")) | I6: =IF(I5<Inputs!C19,"Develop",IF(I5<Inputs!C19+Inputs!C25,"Produce","-")) | J6: =IF(J5<Inputs!C19,"Develop",IF(J5<Inputs!C19+Inputs!C25,"Produce","-")) | K6: =IF(K5<Inputs!C19,"Develop",IF(K5<Inputs!C19+Inputs!C25,"Produce","-")) | L6: =IF(L5<Inputs!C19,"Develop",IF(L5<Inputs!C19+Inputs!C25,"Produce","-")) | M6: =IF(M5<Inputs!C19,"Develop",IF(M5<Inputs!C19+Inputs!C25,"Produce","-")) | N6: =IF(N5<Inputs!C19,"Develop",IF(N5<Inputs!C19+Inputs!C25,"Produce","-")) | O6: =IF(O5<Inputs!C19,"Develop",IF(O5<Inputs!C19+Inputs!C25,"Produce","-")) | P6: =IF(P5<Inputs!C19,"Develop",IF(P5<Inputs!C19+Inputs!C25,"Produce","-")) | Q6: =IF(Q5<Inputs!C19,"Develop",IF(Q5<Inputs!C19+Inputs!C25,"Produce","-")) | R6: =IF(R5<Inputs!C19,"Develop",IF(R5<Inputs!C19+Inputs!C25,"Produce","-")) | S6: =IF(S5<Inputs!C19,"Develop",IF(S5<Inputs!C19+Inputs!C25,"Produce","-")) | T6: =IF(T5<Inputs!C19,"Develop",IF(T5<Inputs!C19+Inputs!C25,"Produce","-")) | U6: =IF(U5<Inputs!C19,"Develop",IF(U5<Inputs!C19+Inputs!C25,"Produce","-")) | V6: =IF(V5<Inputs!C19,"Develop",IF(V5<Inputs!C19+Inputs!C25,"Produce","-")) | W6: =IF(W5<Inputs!C19,"Develop",IF(W5<Inputs!C19+Inputs!C25,"Produce","-")) | X6: =IF(X5<Inputs!C19,"Develop",IF(X5<Inputs!C19+Inputs!C25,"Produce","-")) | Y6: =IF(Y5<Inputs!C19,"Develop",IF(Y5<Inputs!C19+Inputs!C25,"Produce","-")) | Z6: =IF(Z5<Inputs!C19,"Develop",IF(Z5<Inputs!C19+Inputs!C25,"Produce","-"))
A8: PRODUCTION & REVENUE
A9: Production rate (bopd) | B9: =IF(B5<Inputs!C19,0,IF(B5=Inputs!C19,Inputs!C20*Inputs!C21*Inputs!C14,IF(B5<Inputs!C19+Inputs!C22,Inputs!C20*Inputs!C14,IF(B5<Inputs!C19+Inputs!C25,0*(1-Inputs!C23),0)))) | C9: =IF(C5<Inputs!C19,0,IF(C5=Inputs!C19,Inputs!C20*Inputs!C21*Inputs!C14,IF(C5<Inputs!C19+Inputs!C22,Inputs!C20*Inputs!C14,IF(C5<Inputs!C19+Inputs!C25,B9*(1-Inputs!C23),0)))) | D9: =IF(D5<Inputs!C19,0,IF(D5=Inputs!C19,Inputs!C20*Inputs!C21*Inputs!C14,IF(D5<Inputs!C19+Inputs!C22,Inputs!C20*Inputs!C14,IF(D5<Inputs!C19+Inputs!C25,C9*(1-Inputs!C23),0)))) | E9: =IF(E5<Inputs!C19,0,IF(E5=Inputs!C19,Inputs!C20*Inputs!C21*Inputs!C14,IF(E5<Inputs!C19+Inputs!C22,Inputs!C20*Inputs!C14,IF(E5<Inputs!C19+Inputs!C25,D9*(1-Inputs!C23),0)))) | F9: =IF(F5<Inputs!C19,0,IF(F5=Inputs!C19,Inputs!C20*Inputs!C21*Inputs!C14,IF(F5<Inputs!C19+Inputs!C22,Inputs!C20*Inputs!C14,IF(F5<Inputs!C19+Inputs!C25,E9*(1-Inputs!C23),0)))) | G9: =IF(G5<Inputs!C19,0,IF(G5=Inputs!C19,Inputs!C20*Inputs!C21*Inputs!C14,IF(G5<Inputs!C19+Inputs!C22,Inputs!C20*Inputs!C14,IF(G5<Inputs!C19+Inputs!C25,F9*(1-Inputs!C23),0)))) | H9: =IF(H5<Inputs!C19,0,IF(H5=Inputs!C19,Inputs!C20*Inputs!C21*Inputs!C14,IF(H5<Inputs!C19+Inputs!C22,Inputs!C20*Inputs!C14,IF(H5<Inputs!C19+Inputs!C25,G9*(1-Inputs!C23),0)))) | I9: =IF(I5<Inputs!C19,0,IF(I5=Inputs!C19,Inputs!C20*Inputs!C21*Inputs!C14,IF(I5<Inputs!C19+Inputs!C22,Inputs!C20*Inputs!C14,IF(I5<Inputs!C19+Inputs!C25,H9*(1-Inputs!C23),0)))) | J9: =IF(J5<Inputs!C19,0,IF(J5=Inputs!C19,Inputs!C20*Inputs!C21*Inputs!C14,IF(J5<Inputs!C19+Inputs!C22,Inputs!C20*Inputs!C14,IF(J5<Inputs!C19+Inputs!C25,I9*(1-Inputs!C23),0)))) | K9: =IF(K5<Inputs!C19,0,IF(K5=Inputs!C19,Inputs!C20*Inputs!C21*Inputs!C14,IF(K5<Inputs!C19+Inputs!C22,Inputs!C20*Inputs!C14,IF(K5<Inputs!C19+Inputs!C25,J9*(1-Inputs!C23),0)))) | L9: =IF(L5<Inputs!C19,0,IF(L5=Inputs!C19,Inputs!C20*Inputs!C21*Inputs!C14,IF(L5<Inputs!C19+Inputs!C22,Inputs!C20*Inputs!C14,IF(L5<Inputs!C19+Inputs!C25,K9*(1-Inputs!C23),0)))) | M9: =IF(M5<Inputs!C19,0,IF(M5=Inputs!C19,Inputs!C20*Inputs!C21*Inputs!C14,IF(M5<Inputs!C19+Inputs!C22,Inputs!C20*Inputs!C14,IF(M5<Inputs!C19+Inputs!C25,L9*(1-Inputs!C23),0)))) | N9: =IF(N5<Inputs!C19,0,IF(N5=Inputs!C19,Inputs!C20*Inputs!C21*Inputs!C14,IF(N5<Inputs!C19+Inputs!C22,Inputs!C20*Inputs!C14,IF(N5<Inputs!C19+Inputs!C25,M9*(1-Inputs!C23),0)))) | O9: =IF(O5<Inputs!C19,0,IF(O5=Inputs!C19,Inputs!C20*Inputs!C21*Inputs!C14,IF(O5<Inputs!C19+Inputs!C22,Inputs!C20*Inputs!C14,IF(O5<Inputs!C19+Inputs!C25,N9*(1-Inputs!C23),0)))) | P9: =IF(P5<Inputs!C19,0,IF(P5=Inputs!C19,Inputs!C20*Inputs!C21*Inputs!C14,IF(P5<Inputs!C19+Inputs!C22,Inputs!C20*Inputs!C14,IF(P5<Inputs!C19+Inputs!C25,O9*(1-Inputs!C23),0)))) | Q9: =IF(Q5<Inputs!C19,0,IF(Q5=Inputs!C19,Inputs!C20*Inputs!C21*Inputs!C14,IF(Q5<Inputs!C19+Inputs!C22,Inputs!C20*Inputs!C14,IF(Q5<Inputs!C19+Inputs!C25,P9*(1-Inputs!C23),0)))) | R9: =IF(R5<Inputs!C19,0,IF(R5=Inputs!C19,Inputs!C20*Inputs!C21*Inputs!C14,IF(R5<Inputs!C19+Inputs!C22,Inputs!C20*Inputs!C14,IF(R5<Inputs!C19+Inputs!C25,Q9*(1-Inputs!C23),0)))) | S9: =IF(S5<Inputs!C19,0,IF(S5=Inputs!C19,Inputs!C20*Inputs!C21*Inputs!C14,IF(S5<Inputs!C19+Inputs!C22,Inputs!C20*Inputs!C14,IF(S5<Inputs!C19+Inputs!C25,R9*(1-Inputs!C23),0)))) | T9: =IF(T5<Inputs!C19,0,IF(T5=Inputs!C19,Inputs!C20*Inputs!C21*Inputs!C14,IF(T5<Inputs!C19+Inputs!C22,Inputs!C20*Inputs!C14,IF(T5<Inputs!C19+Inputs!C25,S9*(1-Inputs!C23),0)))) | U9: =IF(U5<Inputs!C19,0,IF(U5=Inputs!C19,Inputs!C20*Inputs!C21*Inputs!C14,IF(U5<Inputs!C19+Inputs!C22,Inputs!C20*Inputs!C14,IF(U5<Inputs!C19+Inputs!C25,T9*(1-Inputs!C23),0)))) | V9: =IF(V5<Inputs!C19,0,IF(V5=Inputs!C19,Inputs!C20*Inputs!C21*Inputs!C14,IF(V5<Inputs!C19+Inputs!C22,Inputs!C20*Inputs!C14,IF(V5<Inputs!C19+Inputs!C25,U9*(1-Inputs!C23),0)))) | W9: =IF(W5<Inputs!C19,0,IF(W5=Inputs!C19,Inputs!C20*Inputs!C21*Inputs!C14,IF(W5<Inputs!C19+Inputs!C22,Inputs!C20*Inputs!C14,IF(W5<Inputs!C19+Inputs!C25,V9*(1-Inputs!C23),0)))) | X9: =IF(X5<Inputs!C19,0,IF(X5=Inputs!C19,Inputs!C20*Inputs!C21*Inputs!C14,IF(X5<Inputs!C19+Inputs!C22,Inputs!C20*Inputs!C14,IF(X5<Inputs!C19+Inputs!C25,W9*(1-Inputs!C23),0)))) | Y9: =IF(Y5<Inputs!C19,0,IF(Y5=Inputs!C19,Inputs!C20*Inputs!C21*Inputs!C14,IF(Y5<Inputs!C19+Inputs!C22,Inputs!C20*Inputs!C14,IF(Y5<Inputs!C19+Inputs!C25,X9*(1-Inputs!C23),0)))) | Z9: =IF(Z5<Inputs!C19,0,IF(Z5=Inputs!C19,Inputs!C20*Inputs!C21*Inputs!C14,IF(Z5<Inputs!C19+Inputs!C22,Inputs!C20*Inputs!C14,IF(Z5<Inputs!C19+Inputs!C25,Y9*(1-Inputs!C23),0))))
A10: Annual production (mmbbl) | B10: =B9*Inputs!C24/1000000 | C10: =C9*Inputs!C24/1000000 | D10: =D9*Inputs!C24/1000000 | E10: =E9*Inputs!C24/1000000 | F10: =F9*Inputs!C24/1000000 | G10: =G9*Inputs!C24/1000000 | H10: =H9*Inputs!C24/1000000 | I10: =I9*Inputs!C24/1000000 | J10: =J9*Inputs!C24/1000000 | K10: =K9*Inputs!C24/1000000 | L10: =L9*Inputs!C24/1000000 | M10: =M9*Inputs!C24/1000000 | N10: =N9*Inputs!C24/1000000 | O10: =O9*Inputs!C24/1000000 | P10: =P9*Inputs!C24/1000000 | Q10: =Q9*Inputs!C24/1000000 | R10: =R9*Inputs!C24/1000000 | S10: =S9*Inputs!C24/1000000 | T10: =T9*Inputs!C24/1000000 | U10: =U9*Inputs!C24/1000000 | V10: =V9*Inputs!C24/1000000 | W10: =W9*Inputs!C24/1000000 | X10: =X9*Inputs!C24/1000000 | Y10: =Y9*Inputs!C24/1000000 | Z10: =Z9*Inputs!C24/1000000
A11: Oil price ($/bbl) | B11: =Inputs!C28 | C11: =Inputs!C28 | D11: =Inputs!C28 | E11: =Inputs!C28 | F11: =Inputs!C28 | G11: =Inputs!C28 | H11: =Inputs!C28 | I11: =Inputs!C28 | J11: =Inputs!C28 | K11: =Inputs!C28 | L11: =Inputs!C28 | M11: =Inputs!C28 | N11: =Inputs!C28 | O11: =Inputs!C28 | P11: =Inputs!C28 | Q11: =Inputs!C28 | R11: =Inputs!C28 | S11: =Inputs!C28 | T11: =Inputs!C28 | U11: =Inputs!C28 | V11: =Inputs!C28 | W11: =Inputs!C28 | X11: =Inputs!C28 | Y11: =Inputs!C28 | Z11: =Inputs!C28
A12: Gross revenue | B12: =B10*B11 | C12: =C10*C11 | D12: =D10*D11 | E12: =E10*E11 | F12: =F10*F11 | G12: =G10*G11 | H12: =H10*H11 | I12: =I10*I11 | ... Z12: =Z10*Z11
A14: ROYALTIES, OPEX & TAX
A15: Production royalty | B15: =-B12*Inputs!C34 | C15: =-C12*Inputs!C34 | D15: =-D12*Inputs!C34 | E15: =-E12*Inputs!C34 | F15: =-F12*Inputs!C34 | G15: =-G12*Inputs!C34 | H15: =-H12*Inputs!C34 | I15: =-I12*Inputs!C34 | J15: =-J12*Inputs!C34 | K15: =-K12*Inputs!C34 | L15: =-L12*Inputs!C34 | M15: =-M12*Inputs!C34 | N15: =-N12*Inputs!C34 | O15: =-O12*Inputs!C34 | P15: =-P12*Inputs!C34 | Q15: =-Q12*Inputs!C34 | R15: =-R12*Inputs!C34 | S15: =-S12*Inputs!C34 | T15: =-T12*Inputs!C34 | U15: =-U12*Inputs!C34 | V15: =-V12*Inputs!C34 | W15: =-W12*Inputs!C34 | X15: =-X12*Inputs!C34 | Y15: =-Y12*Inputs!C34 | Z15: =-Z12*Inputs!C34
A16: Price-based royalty | B16: =-B12*Inputs!C35 | C16: =-C12*Inputs!C35 | D16: =-D12*Inputs!C35 | E16: =-E12*Inputs!C35 | F16: =-F12*Inputs!C35 | G16: =-G12*Inputs!C35 | H16: =-H12*Inputs!C35 | I16: =-I12*Inputs!C35 | J16: =-J12*Inputs!C35 | K16: =-K12*Inputs!C35 | L16: =-L12*Inputs!C35 | M16: =-M12*Inputs!C35 | N16: =-N12*Inputs!C35 | O16: =-O12*Inputs!C35 | P16: =-P12*Inputs!C35 | Q16: =-Q12*Inputs!C35 | R16: =-R12*Inputs!C35 | S16: =-S12*Inputs!C35 | T16: =-T12*Inputs!C35 | U16: =-U12*Inputs!C35 | V16: =-V12*Inputs!C35 | W16: =-W12*Inputs!C35 | X16: =-X12*Inputs!C35 | Y16: =-Y12*Inputs!C35 | Z16: =-Z12*Inputs!C35
A17: Net revenue after royalty | B17: =B12+B15+B16 | C17: =C12+C15+C16 | D17: =D12+D15+D16 | E17: =E12+E15+E16 | F17: =F12+F15+F16 | G17: =G12+G15+G16 | H17: =H12+H15+H16 | I17: =I12+I15+I16 | ... Z17: =Z12+Z15+Z16
A18: Variable opex | B18: =-B10*Inputs!C29 | C18: =-C10*Inputs!C29 | D18: =-D10*Inputs!C29 | E18: =-E10*Inputs!C29 | F18: =-F10*Inputs!C29 | G18: =-G10*Inputs!C29 | H18: =-H10*Inputs!C29 | I18: =-I10*Inputs!C29 | J18: =-J10*Inputs!C29 | K18: =-K10*Inputs!C29 | L18: =-L10*Inputs!C29 | M18: =-M10*Inputs!C29 | N18: =-N10*Inputs!C29 | O18: =-O10*Inputs!C29 | P18: =-P10*Inputs!C29 | Q18: =-Q10*Inputs!C29 | R18: =-R10*Inputs!C29 | S18: =-S10*Inputs!C29 | T18: =-T10*Inputs!C29 | U18: =-U10*Inputs!C29 | V18: =-V10*Inputs!C29 | W18: =-W10*Inputs!C29 | X18: =-X10*Inputs!C29 | Y18: =-Y10*Inputs!C29 | Z18: =-Z10*Inputs!C29
A19: Fixed opex | B19: =-IF(AND(B5>=Inputs!C19,B5<Inputs!C19+Inputs!C25),Inputs!C30,0) | C19: =-IF(AND(C5>=Inputs!C19,C5<Inputs!C19+Inputs!C25),Inputs!C30,0) | D19: =-IF(AND(D5>=Inputs!C19,D5<Inputs!C19+Inputs!C25),Inputs!C30,0) | E19: =-IF(AND(E5>=Inputs!C19,E5<Inputs!C19+Inputs!C25),Inputs!C30,0) | F19: =-IF(AND(F5>=Inputs!C19,F5<Inputs!C19+Inputs!C25),Inputs!C30,0) | G19: =-IF(AND(G5>=Inputs!C19,G5<Inputs!C19+Inputs!C25),Inputs!C30,0) | H19: =-IF(AND(H5>=Inputs!C19,H5<Inputs!C19+Inputs!C25),Inputs!C30,0) | I19: =-IF(AND(I5>=Inputs!C19,I5<Inputs!C19+Inputs!C25),Inputs!C30,0) | J19: =-IF(AND(J5>=Inputs!C19,J5<Inputs!C19+Inputs!C25),Inputs!C30,0) | K19: =-IF(AND(K5>=Inputs!C19,K5<Inputs!C19+Inputs!C25),Inputs!C30,0) | L19: =-IF(AND(L5>=Inputs!C19,L5<Inputs!C19+Inputs!C25),Inputs!C30,0) | M19: =-IF(AND(M5>=Inputs!C19,M5<Inputs!C19+Inputs!C25),Inputs!C30,0) | N19: =-IF(AND(N5>=Inputs!C19,N5<Inputs!C19+Inputs!C25),Inputs!C30,0) | O19: =-IF(AND(O5>=Inputs!C19,O5<Inputs!C19+Inputs!C25),Inputs!C30,0) | P19: =-IF(AND(P5>=Inputs!C19,P5<Inputs!C19+Inputs!C25),Inputs!C30,0) | Q19: =-IF(AND(Q5>=Inputs!C19,Q5<Inputs!C19+Inputs!C25),Inputs!C30,0) | R19: =-IF(AND(R5>=Inputs!C19,R5<Inputs!C19+Inputs!C25),Inputs!C30,0) | S19: =-IF(AND(S5>=Inputs!C19,S5<Inputs!C19+Inputs!C25),Inputs!C30,0) | T19: =-IF(AND(T5>=Inputs!C19,T5<Inputs!C19+Inputs!C25),Inputs!C30,0) | U19: =-IF(AND(U5>=Inputs!C19,U5<Inputs!C19+Inputs!C25),Inputs!C30,0) | V19: =-IF(AND(V5>=Inputs!C19,V5<Inputs!C19+Inputs!C25),Inputs!C30,0) | W19: =-IF(AND(W5>=Inputs!C19,W5<Inputs!C19+Inputs!C25),Inputs!C30,0) | X19: =-IF(AND(X5>=Inputs!C19,X5<Inputs!C19+Inputs!C25),Inputs!C30,0) | Y19: =-IF(AND(Y5>=Inputs!C19,Y5<Inputs!C19+Inputs!C25),Inputs!C30,0) | Z19: =-IF(AND(Z5>=Inputs!C19,Z5<Inputs!C19+Inputs!C25),Inputs!C30,0)
A20: Capital allowance (depreciation) | B20: =IF(AND(B5>=Inputs!C19,B5<Inputs!C19+Inputs!C38),Inputs!C15/Inputs!C38,0) | C20: =IF(AND(C5>=Inputs!C19,C5<Inputs!C19+Inputs!C38),Inputs!C15/Inputs!C38,0) | D20: =IF(AND(D5>=Inputs!C19,D5<Inputs!C19+Inputs!C38),Inputs!C15/Inputs!C38,0) | E20: =IF(AND(E5>=Inputs!C19,E5<Inputs!C19+Inputs!C38),Inputs!C15/Inputs!C38,0) | F20: =IF(AND(F5>=Inputs!C19,F5<Inputs!C19+Inputs!C38),Inputs!C15/Inputs!C38,0) | G20: =IF(AND(G5>=Inputs!C19,G5<Inputs!C19+Inputs!C38),Inputs!C15/Inputs!C38,0) | H20: =IF(AND(H5>=Inputs!C19,H5<Inputs!C19+Inputs!C38),Inputs!C15/Inputs!C38,0) | I20: =IF(AND(I5>=Inputs!C19,I5<Inputs!C19+Inputs!C38),Inputs!C15/Inputs!C38,0) | J20: =IF(AND(J5>=Inputs!C19,J5<Inputs!C19+Inputs!C38),Inputs!C15/Inputs!C38,0) | K20: =IF(AND(K5>=Inputs!C19,K5<Inputs!C19+Inputs!C38),Inputs!C15/Inputs!C38,0) | L20: =IF(AND(L5>=Inputs!C19,L5<Inputs!C19+Inputs!C38),Inputs!C15/Inputs!C38,0) | M20: =IF(AND(M5>=Inputs!C19,M5<Inputs!C19+Inputs!C38),Inputs!C15/Inputs!C38,0) | N20: =IF(AND(N5>=Inputs!C19,N5<Inputs!C19+Inputs!C38),Inputs!C15/Inputs!C38,0) | O20: =IF(AND(O5>=Inputs!C19,O5<Inputs!C19+Inputs!C38),Inputs!C15/Inputs!C38,0) | P20: =IF(AND(P5>=Inputs!C19,P5<Inputs!C19+Inputs!C38),Inputs!C15/Inputs!C38,0) | Q20: =IF(AND(Q5>=Inputs!C19,Q5<Inputs!C19+Inputs!C38),Inputs!C15/Inputs!C38,0) | R20: =IF(AND(R5>=Inputs!C19,R5<Inputs!C19+Inputs!C38),Inputs!C15/Inputs!C38,0) | S20: =IF(AND(S5>=Inputs!C19,S5<Inputs!C19+Inputs!C38),Inputs!C15/Inputs!C38,0) | T20: =IF(AND(T5>=Inputs!C19,T5<Inputs!C19+Inputs!C38),Inputs!C15/Inputs!C38,0) | U20: =IF(AND(U5>=Inputs!C19,U5<Inputs!C19+Inputs!C38),Inputs!C15/Inputs!C38,0) | V20: =IF(AND(V5>=Inputs!C19,V5<Inputs!C19+Inputs!C38),Inputs!C15/Inputs!C38,0) | W20: =IF(AND(W5>=Inputs!C19,W5<Inputs!C19+Inputs!C38),Inputs!C15/Inputs!C38,0) | X20: =IF(AND(X5>=Inputs!C19,X5<Inputs!C19+Inputs!C38),Inputs!C15/Inputs!C38,0) | Y20: =IF(AND(Y5>=Inputs!C19,Y5<Inputs!C19+Inputs!C38),Inputs!C15/Inputs!C38,0) | Z20: =IF(AND(Z5>=Inputs!C19,Z5<Inputs!C19+Inputs!C38),Inputs!C15/Inputs!C38,0)
A21: Taxable profit (pre-loss c/f) | B21: =B17+B18+B19-B20 | C21: =C17+C18+C19-C20 | D21: =D17+D18+D19-D20 | E21: =E17+E18+E19-E20 | F21: =F17+F18+F19-F20 | G21: =G17+G18+G19-G20 | H21: =H17+H18+H19-H20 | I21: =I17+I18+I19-I20 | ... Z21: =Z17+Z18+Z19-Z20
A22: Loss c/f balance | B22: =MAX(0,0-MAX(0,B21))+MAX(0,-B21) | C22: =MAX(0,B22-MAX(0,C21))+MAX(0,-C21) | D22: =MAX(0,C22-MAX(0,D21))+MAX(0,-D21) | E22: =MAX(0,D22-MAX(0,E21))+MAX(0,-E21) | F22: =MAX(0,E22-MAX(0,F21))+MAX(0,-F21) | G22: =MAX(0,F22-MAX(0,G21))+MAX(0,-G21) | H22: =MAX(0,G22-MAX(0,H21))+MAX(0,-H21) | I22: =MAX(0,H22-MAX(0,I21))+MAX(0,-I21) | J22: =MAX(0,I22-MAX(0,J21))+MAX(0,-J21) | ... Z22: =MAX(0,Y22-MAX(0,Z21))+MAX(0,-Z21)
A23: Taxable base | B23: =MAX(0,B21-0) | C23: =MAX(0,C21-B22) | D23: =MAX(0,D21-C22) | E23: =MAX(0,E21-D22) | F23: =MAX(0,F21-E22) | G23: =MAX(0,G21-F22) | H23: =MAX(0,H21-G22) | I23: =MAX(0,I21-H22) | J23: =MAX(0,J21-I22) | ... Z23: =MAX(0,Z21-Y22)
A24: Hydrocarbon tax + CIT | B24: =-(B23*Inputs!C36+(B23-B23*Inputs!C36)*Inputs!C37) | C24: =-(C23*Inputs!C36+(C23-C23*Inputs!C36)*Inputs!C37) | D24: =-(D23*Inputs!C36+(D23-D23*Inputs!C36)*Inputs!C37) | E24: =-(E23*Inputs!C36+(E23-E23*Inputs!C36)*Inputs!C37) | F24: =-(F23*Inputs!C36+(F23-F23*Inputs!C36)*Inputs!C37) | G24: =-(G23*Inputs!C36+(G23-G23*Inputs!C36)*Inputs!C37) | H24: =-(H23*Inputs!C36+(H23-H23*Inputs!C36)*Inputs!C37) | I24: =-(I23*Inputs!C36+(I23-I23*Inputs!C36)*Inputs!C37) | J24: =-(J23*Inputs!C36+(J23-J23*Inputs!C36)*Inputs!C37) | K24: =-(K23*Inputs!C36+(K23-K23*Inputs!C36)*Inputs!C37) | L24: =-(L23*Inputs!C36+(L23-L23*Inputs!C36)*Inputs!C37) | M24: =-(M23*Inputs!C36+(M23-M23*Inputs!C36)*Inputs!C37) | N24: =-(N23*Inputs!C36+(N23-N23*Inputs!C36)*Inputs!C37) | O24: =-(O23*Inputs!C36+(O23-O23*Inputs!C36)*Inputs!C37) | P24: =-(P23*Inputs!C36+(P23-P23*Inputs!C36)*Inputs!C37) | Q24: =-(Q23*Inputs!C36+(Q23-Q23*Inputs!C36)*Inputs!C37) | R24: =-(R23*Inputs!C36+(R23-R23*Inputs!C36)*Inputs!C37) | S24: =-(S23*Inputs!C36+(S23-S23*Inputs!C36)*Inputs!C37) | T24: =-(T23*Inputs!C36+(T23-T23*Inputs!C36)*Inputs!C37) | U24: =-(U23*Inputs!C36+(U23-U23*Inputs!C36)*Inputs!C37) | V24: =-(V23*Inputs!C36+(V23-V23*Inputs!C36)*Inputs!C37) | W24: =-(W23*Inputs!C36+(W23-W23*Inputs!C36)*Inputs!C37) | X24: =-(X23*Inputs!C36+(X23-X23*Inputs!C36)*Inputs!C37) | Y24: =-(Y23*Inputs!C36+(Y23-Y23*Inputs!C36)*Inputs!C37) | Z24: =-(Z23*Inputs!C36+(Z23-Z23*Inputs!C36)*Inputs!C37)
A26: CASH FLOW & WATERFALL
A27: Net operating cash flow | B27: =B17+B18+B19+B24 | C27: =C17+C18+C19+C24 | D27: =D17+D18+D19+D24 | E27: =E17+E18+E19+E24 | F27: =F17+F18+F19+F24 | G27: =G17+G18+G19+G24 | H27: =H17+H18+H19+H24 | I27: =I17+I18+I19+I24 | ... Z27: =Z17+Z18+Z19+Z24
A28: Capital expenditure | B28: =-IF(B5=1,Inputs!C15*Inputs!C18,IF(B5=2,Inputs!C15*(1-Inputs!C18),0)) | C28: =-IF(C5=1,Inputs!C15*Inputs!C18,IF(C5=2,Inputs!C15*(1-Inputs!C18),0)) | D28: =-IF(D5=1,Inputs!C15*Inputs!C18,IF(D5=2,Inputs!C15*(1-Inputs!C18),0)) | E28: =-IF(E5=1,Inputs!C15*Inputs!C18,IF(E5=2,Inputs!C15*(1-Inputs!C18),0)) | F28: =-IF(F5=1,Inputs!C15*Inputs!C18,IF(F5=2,Inputs!C15*(1-Inputs!C18),0)) | G28: =-IF(G5=1,Inputs!C15*Inputs!C18,IF(G5=2,Inputs!C15*(1-Inputs!C18),0)) | H28: =-IF(H5=1,Inputs!C15*Inputs!C18,IF(H5=2,Inputs!C15*(1-Inputs!C18),0)) | I28: =-IF(I5=1,Inputs!C15*Inputs!C18,IF(I5=2,Inputs!C15*(1-Inputs!C18),0)) | J28: =-IF(J5=1,Inputs!C15*Inputs!C18,IF(J5=2,Inputs!C15*(1-Inputs!C18),0)) | K28: =-IF(K5=1,Inputs!C15*Inputs!C18,IF(K5=2,Inputs!C15*(1-Inputs!C18),0)) | L28: =-IF(L5=1,Inputs!C15*Inputs!C18,IF(L5=2,Inputs!C15*(1-Inputs!C18),0)) | M28: =-IF(M5=1,Inputs!C15*Inputs!C18,IF(M5=2,Inputs!C15*(1-Inputs!C18),0)) | N28: =-IF(N5=1,Inputs!C15*Inputs!C18,IF(N5=2,Inputs!C15*(1-Inputs!C18),0)) | O28: =-IF(O5=1,Inputs!C15*Inputs!C18,IF(O5=2,Inputs!C15*(1-Inputs!C18),0)) | P28: =-IF(P5=1,Inputs!C15*Inputs!C18,IF(P5=2,Inputs!C15*(1-Inputs!C18),0)) | Q28: =-IF(Q5=1,Inputs!C15*Inputs!C18,IF(Q5=2,Inputs!C15*(1-Inputs!C18),0)) | R28: =-IF(R5=1,Inputs!C15*Inputs!C18,IF(R5=2,Inputs!C15*(1-Inputs!C18),0)) | S28: =-IF(S5=1,Inputs!C15*Inputs!C18,IF(S5=2,Inputs!C15*(1-Inputs!C18),0)) | T28: =-IF(T5=1,Inputs!C15*Inputs!C18,IF(T5=2,Inputs!C15*(1-Inputs!C18),0)) | U28: =-IF(U5=1,Inputs!C15*Inputs!C18,IF(U5=2,Inputs!C15*(1-Inputs!C18),0)) | V28: =-IF(V5=1,Inputs!C15*Inputs!C18,IF(V5=2,Inputs!C15*(1-Inputs!C18),0)) | W28: =-IF(W5=1,Inputs!C15*Inputs!C18,IF(W5=2,Inputs!C15*(1-Inputs!C18),0)) | X28: =-IF(X5=1,Inputs!C15*Inputs!C18,IF(X5=2,Inputs!C15*(1-Inputs!C18),0)) | Y28: =-IF(Y5=1,Inputs!C15*Inputs!C18,IF(Y5=2,Inputs!C15*(1-Inputs!C18),0)) | Z28: =-IF(Z5=1,Inputs!C15*Inputs!C18,IF(Z5=2,Inputs!C15*(1-Inputs!C18),0))
A29: Project net cash flow | B29: =B27+B28 | C29: =C27+C28 | D29: =D27+D28 | E29: =E27+E28 | F29: =F27+F28 | G29: =G27+G28 | H29: =H27+H28 | I29: =I27+I28 | ... Z29: =Z27+Z28
A31: Cumulative capital recovered (investor) | B31: =0+B33 | C31: =B31+C33 | D31: =C31+D33 | E31: =D31+E33 | F31: =E31+F33 | G31: =F31+G33 | H31: =G31+H33 | I31: =H31+I33 | J31: =I31+J33 | ... Z31: =Y31+Z33
A32: Gross cash in recovery mode | B32: =MAX(0,MIN(B27,MAX(0,Inputs!C15-0)/Inputs!C41)) | C32: =MAX(0,MIN(C27,MAX(0,Inputs!C15-B31)/Inputs!C41)) | D32: =MAX(0,MIN(D27,MAX(0,Inputs!C15-C31)/Inputs!C41)) | E32: =MAX(0,MIN(E27,MAX(0,Inputs!C15-D31)/Inputs!C41)) | F32: =MAX(0,MIN(F27,MAX(0,Inputs!C15-E31)/Inputs!C41)) | G32: =MAX(0,MIN(G27,MAX(0,Inputs!C15-F31)/Inputs!C41)) | H32: =MAX(0,MIN(H27,MAX(0,Inputs!C15-G31)/Inputs!C41)) | I32: =MAX(0,MIN(I27,MAX(0,Inputs!C15-H31)/Inputs!C41)) | J32: =MAX(0,MIN(J27,MAX(0,Inputs!C15-I31)/Inputs!C41)) | K32: =MAX(0,MIN(K27,MAX(0,Inputs!C15-J31)/Inputs!C41)) | L32: =MAX(0,MIN(L27,MAX(0,Inputs!C15-K31)/Inputs!C41)) | M32: =MAX(0,MIN(M27,MAX(0,Inputs!C15-L31)/Inputs!C41)) | N32: =MAX(0,MIN(N27,MAX(0,Inputs!C15-M31)/Inputs!C41)) | O32: =MAX(0,MIN(O27,MAX(0,Inputs!C15-N31)/Inputs!C41)) | P32: =MAX(0,MIN(P27,MAX(0,Inputs!C15-O31)/Inputs!C41)) | Q32: =MAX(0,MIN(Q27,MAX(0,Inputs!C15-P31)/Inputs!C41)) | R32: =MAX(0,MIN(R27,MAX(0,Inputs!C15-Q31)/Inputs!C41)) | S32: =MAX(0,MIN(S27,MAX(0,Inputs!C15-R31)/Inputs!C41)) | T32: =MAX(0,MIN(T27,MAX(0,Inputs!C15-S31)/Inputs!C41)) | U32: =MAX(0,MIN(U27,MAX(0,Inputs!C15-T31)/Inputs!C41)) | V32: =MAX(0,MIN(V27,MAX(0,Inputs!C15-U31)/Inputs!C41)) | W32: =MAX(0,MIN(W27,MAX(0,Inputs!C15-V31)/Inputs!C41)) | X32: =MAX(0,MIN(X27,MAX(0,Inputs!C15-W31)/Inputs!C41)) | Y32: =MAX(0,MIN(Y27,MAX(0,Inputs!C15-X31)/Inputs!C41)) | Z32: =MAX(0,MIN(Z27,MAX(0,Inputs!C15-Y31)/Inputs!C41))
A33: → to investor (capital recovery) | B33: =B32*Inputs!C41 | C33: =C32*Inputs!C41 | D33: =D32*Inputs!C41 | E33: =E32*Inputs!C41 | F33: =F32*Inputs!C41 | G33: =G32*Inputs!C41 | H33: =H32*Inputs!C41 | I33: =I32*Inputs!C41 | J33: =J32*Inputs!C41 | K33: =K32*Inputs!C41 | L33: =L32*Inputs!C41 | M33: =M32*Inputs!C41 | N33: =N32*Inputs!C41 | O33: =O32*Inputs!C41 | P33: =P32*Inputs!C41 | Q33: =Q32*Inputs!C41 | R33: =R32*Inputs!C41 | S33: =S32*Inputs!C41 | T33: =T32*Inputs!C41 | U33: =U32*Inputs!C41 | V33: =V32*Inputs!C41 | W33: =W32*Inputs!C41 | X33: =X32*Inputs!C41 | Y33: =Y32*Inputs!C41 | Z33: =Z32*Inputs!C41
A34: → to Onterra (incentive) | B34: =B32*Inputs!C42 | C34: =C32*Inputs!C42 | D34: =D32*Inputs!C42 | E34: =E32*Inputs!C42 | F34: =F32*Inputs!C42 | G34: =G32*Inputs!C42 | H34: =H32*Inputs!C42 | I34: =I32*Inputs!C42 | J34: =J32*Inputs!C42 | K34: =K32*Inputs!C42 | L34: =L32*Inputs!C42 | M34: =M32*Inputs!C42 | N34: =N32*Inputs!C42 | O34: =O32*Inputs!C42 | P34: =P32*Inputs!C42 | Q34: =Q32*Inputs!C42 | R34: =R32*Inputs!C42 | S34: =S32*Inputs!C42 | T34: =T32*Inputs!C42 | U34: =U32*Inputs!C42 | V34: =V32*Inputs!C42 | W34: =W32*Inputs!C42 | X34: =X32*Inputs!C42 | Y34: =Y32*Inputs!C42 | Z34: =Z32*Inputs!C42
A35: Leftover cash (post-recovery) | B35: =MAX(0,B27-B32) | C35: =MAX(0,C27-C32) | D35: =MAX(0,D27-D32) | E35: =MAX(0,E27-E32) | F35: =MAX(0,F27-F32) | G35: =MAX(0,G27-G32) | H35: =MAX(0,H27-H32) | I35: =MAX(0,I27-I32) | ... Z35: =MAX(0,Z27-Z32)
A36: → to Onterra (promote) | B36: =B35*Inputs!C44 | C36: =C35*Inputs!C44 | D36: =D35*Inputs!C44 | E36: =E35*Inputs!C44 | F36: =F35*Inputs!C44 | G36: =G35*Inputs!C44 | H36: =H35*Inputs!C44 | I36: =I35*Inputs!C44 | J36: =J35*Inputs!C44 | K36: =K35*Inputs!C44 | L36: =L35*Inputs!C44 | M36: =M35*Inputs!C44 | N36: =N35*Inputs!C44 | O36: =O35*Inputs!C44 | P36: =P35*Inputs!C44 | Q36: =Q35*Inputs!C44 | R36: =R35*Inputs!C44 | S36: =S35*Inputs!C44 | T36: =T35*Inputs!C44 | U36: =U35*Inputs!C44 | V36: =V35*Inputs!C44 | W36: =W35*Inputs!C44 | X36: =X35*Inputs!C44 | Y36: =Y35*Inputs!C44 | Z36: =Z35*Inputs!C44
A37: → to investor | B37: =B35*Inputs!C43 | C37: =C35*Inputs!C43 | D37: =D35*Inputs!C43 | E37: =E35*Inputs!C43 | F37: =F35*Inputs!C43 | G37: =G35*Inputs!C43 | H37: =H35*Inputs!C43 | I37: =I35*Inputs!C43 | J37: =J35*Inputs!C43 | K37: =K35*Inputs!C43 | L37: =L35*Inputs!C43 | M37: =M35*Inputs!C43 | N37: =N35*Inputs!C43 | O37: =O35*Inputs!C43 | P37: =P35*Inputs!C43 | Q37: =Q35*Inputs!C43 | R37: =R35*Inputs!C43 | S37: =S35*Inputs!C43 | T37: =T35*Inputs!C43 | U37: =U35*Inputs!C43 | V37: =V35*Inputs!C43 | W37: =W35*Inputs!C43 | X37: =X35*Inputs!C43 | Y37: =Y35*Inputs!C43 | Z37: =Z35*Inputs!C43
A39: INVESTOR & OPERATOR CASH FLOWS
A40: Investor net cash flow | B40: =B28+B33+B37 | C40: =C28+C33+C37 | D40: =D28+D33+D37 | E40: =E28+E33+E37 | F40: =F28+F33+F37 | G40: =G28+G33+G37 | H40: =H28+H33+H37 | I40: =I28+I33+I37 | ... Z40: =Z28+Z33+Z37
A41: Investor cumulative cash flow | B41: =0+B40 | C41: =B41+C40 | D41: =C41+D40 | E41: =D41+E40 | F41: =E41+F40 | G41: =F41+G40 | H41: =G41+H40 | I41: =H41+I40 | J41: =I41+J40 | ... Z41: =Y41+Z40
A42: Onterra net cash flow (carry/promote) | B42: =B34+B36 | C42: =C34+C36 | D42: =D34+D36 | E42: =E34+E36 | F42: =F34+F36 | G42: =G34+G36 | H42: =H34+H36 | I42: =I34+I36 | ... Z42: =Z34+Z36
A43: Discount factor | B43: =1/(1+Inputs!C31)^B5 | C43: =1/(1+Inputs!C31)^C5 | D43: =1/(1+Inputs!C31)^D5 | E43: =1/(1+Inputs!C31)^E5 | F43: =1/(1+Inputs!C31)^F5 | G43: =1/(1+Inputs!C31)^G5 | H43: =1/(1+Inputs!C31)^H5 | I43: =1/(1+Inputs!C31)^I5 | J43: =1/(1+Inputs!C31)^J5 | K43: =1/(1+Inputs!C31)^K5 | L43: =1/(1+Inputs!C31)^L5 | M43: =1/(1+Inputs!C31)^M5 | N43: =1/(1+Inputs!C31)^N5 | O43: =1/(1+Inputs!C31)^O5 | P43: =1/(1+Inputs!C31)^P5 | Q43: =1/(1+Inputs!C31)^Q5 | R43: =1/(1+Inputs!C31)^R5 | S43: =1/(1+Inputs!C31)^S5 | T43: =1/(1+Inputs!C31)^T5 | U43: =1/(1+Inputs!C31)^U5 | V43: =1/(1+Inputs!C31)^V5 | W43: =1/(1+Inputs!C31)^W5 | X43: =1/(1+Inputs!C31)^X5 | Y43: =1/(1+Inputs!C31)^Y5 | Z43: =1/(1+Inputs!C31)^Z5

Sheet Returns
B2: RETURNS SUMMARY (base case)
B3: Key outputs — all driven by the Inputs sheet
B5: PROJECT ECONOMICS
B6: Total capital to first oil ($m) | C6: =-SUM(Model!B28:Z28) | D6: Investor-funded
B7: Total gross revenue ($m) | C7: =SUM(Model!B12:Z12) | D7: Field life
B8: Total royalties + tax ($m) | C8: =-SUM(Model!B15:Z15)-SUM(Model!B16:Z16)-SUM(Model!B24:Z24) | D8: Government take
B9: Government take (% of revenue) | C9: =(-SUM(Model!B15:Z15)-SUM(Model!B16:Z16)-SUM(Model!B24:Z24))/SUM(Model!B12:Z12)
B10: Total net operating cash ($m) | C10: =SUM(Model!B27:Z27)
B11: Lifetime production (mmbbl) | C11: =SUM(Model!B10:Z10)
B12: Average production (bopd) | C12: =SUM(Model!B10:Z10)*1000000/Inputs!C25/Inputs!C24 | D12: Over field life
B14: INVESTOR RETURNS
B15: Capital invested ($m) | C15: =-SUM(Model!B28:Z28)
B16: Total cash returned to investor ($m) | C16: =SUM(Model!B33:Z33)+SUM(Model!B37:Z37)
B17: Net profit to investor ($m) | C17: =SUM(Model!B33:Z33)+SUM(Model!B37:Z37)+SUM(Model!B28:Z28)
B18: Money multiple (MOIC) | C18: =(SUM(Model!B33:Z33)+SUM(Model!B37:Z37))/(-SUM(Model!B28:Z28))
B19: Investor NPV @ discount rate ($m) | C19: =SUMPRODUCT(Model!B40:Z40,Model!B43:Z43)
B20: Investor IRR | C20: =IRR(Model!B40:Z40) | D20: May show error if cash flows all positive
B21: Payback / cost recovery (yrs from first oil) | C21: =COUNTIF(Model!B41:Z41,"<0")-Inputs!C19+1 | D21: Years of production to full recovery
B23: ONTERRA (OPERATOR) ECONOMICS
B24: Total cash to Onterra ($m) | C24: =SUM(Model!B34:Z34)+SUM(Model!B36:Z36) | D24: No capital at risk (operator promote)
B25: Onterra NPV @ discount rate ($m) | C25: =SUMPRODUCT(Model!B42:Z42,Model!B43:Z43)
B27: UPSIDE LEVER · ADDITIONAL WELLS
B28: This base case assumes a single well. Each additional development well (~$7m onshore to ~$15m offshore) adds production, extends plateau and materially improves field economics. A 3-4 well programme to drain the field optimally is modelled in a client-specific deep-dive on request.
B31: Indicative model for discussion only. PIA 2021 fiscal terms are simplified and must be confirmed with a Nigerian petroleum tax adviser. Not investment advice. All blue cells on the Inputs sheet are editable; the model recalculates automatically.

Sheet Scenarios
B2: OIL PRICE SENSITIVITY (indicative)
B3: Project-level economics scaled by realised price. For exact figures, change the price input on Inputs.
B5: Oil price ($/bbl) | C5: 50 | D5: 60 | E5: 75 | F5: 90 | G5: 100
B6: Gross revenue ($m) | C6: =SUM(Model!B10:Z10)*C5 | D6: =SUM(Model!B10:Z10)*D5 | E6: =SUM(Model!B10:Z10)*E5 | F6: =SUM(Model!B10:Z10)*F5 | G6: =SUM(Model!B10:Z10)*G5
B7: Net cash (approx, $m) | C7: =(C6*(1-Inputs!C34-Inputs!C35))-(SUM(Model!B10:Z10)*Inputs!C29+Inputs!C30*Inputs!C25)-MAX(0,(C6*(1-Inputs!C34-Inputs!C35)-(SUM(Model!B10:Z10)*Inputs!C29+Inputs!C30*Inputs!C25)-Inputs!C15))*(Inputs!C36+(1-Inputs!C36)*Inputs!C37) | D7: =(D6*(1-Inputs!C34-Inputs!C35))-(SUM(Model!B10:Z10)*Inputs!C29+Inputs!C30*Inputs!C25)-MAX(0,(D6*(1-Inputs!C34-Inputs!C35)-(SUM(Model!B10:Z10)*Inputs!C29+Inputs!C30*Inputs!C25)-Inputs!C15))*(Inputs!C36+(1-Inputs!C36)*Inputs!C37) | E7: =(E6*(1-Inputs!C34-Inputs!C35))-(SUM(Model!B10:Z10)*Inputs!C29+Inputs!C30*Inputs!C25)-MAX(0,(E6*(1-Inputs!C34-Inputs!C35)-(SUM(Model!B10:Z10)*Inputs!C29+Inputs!C30*Inputs!C25)-Inputs!C15))*(Inputs!C36+(1-Inputs!C36)*Inputs!C37) | F7: =(F6*(1-Inputs!C34-Inputs!C35))-(SUM(Model!B10:Z10)*Inputs!C29+Inputs!C30*Inputs!C25)-MAX(0,(F6*(1-Inputs!C34-Inputs!C35)-(SUM(Model!B10:Z10)*Inputs!C29+Inputs!C30*Inputs!C25)-Inputs!C15))*(Inputs!C36+(1-Inputs!C36)*Inputs!C37) | G7: =(G6*(1-Inputs!C34-Inputs!C35))-(SUM(Model!B10:Z10)*Inputs!C29+Inputs!C30*Inputs!C25)-MAX(0,(G6*(1-Inputs!C34-Inputs!C35)-(SUM(Model!B10:Z10)*Inputs!C29+Inputs!C30*Inputs!C25)-Inputs!C15))*(Inputs!C36+(1-Inputs!C36)*Inputs!C37)
B8: Net cash vs capital | C8: =C7/Inputs!C15 | D8: =D7/Inputs!C15 | E8: =E7/Inputs!C15 | F8: =F7/Inputs!C15 | G8: =G7/Inputs!C15
B10: Note: this sensitivity is indicative and linear. The dynamic model on the Model/Returns sheets gives the exact, fiscally-correct outcome — change the oil price on Inputs to test a case.
